MCPoly/.DS_Store
MCPoly/__init__.py
MCPoly/lmpset/DataToMolTxt.py
MCPoly/lmpset/DataToXyz.py
MCPoly/lmpset/__init__.py
MCPoly/lmpset/chain.py
MCPoly/lmpset/infchain.py
MCPoly/lmpset/mould.py
MCPoly/lmpset/rebuild.py
MCPoly/moldraw/C_selection.py
MCPoly/moldraw/__init__.py
MCPoly/moldraw/bind_selection.py
MCPoly/moldraw/gui.py
MCPoly/moldraw/molecule.py
MCPoly/moldraw/straight.py
MCPoly/moldraw/sub_selection.py
MCPoly/moldraw/untie.py
MCPoly/orcaset/MolToInp.py
MCPoly/orcaset/XyzToInp.py
MCPoly/orcaset/__init__.py
MCPoly/orcaset/gui.py
MCPoly/orcaset/mgui.py
MCPoly/orcaset/multiorca.py
MCPoly/orcaset/orca.py
MCPoly/orcaset/ssgui.py
MCPoly/orcaset/ssorca.py
MCPoly/orcaset/view3dchoose.py
MCPoly/sscurve/YModulus.py
MCPoly/sscurve/__init__.py
MCPoly/sscurve/gui.py
MCPoly/sscurve/gui2.py
MCPoly/sscurve/multiple.py
MCPoly/sscurve/multiple2.py
MCPoly/sscurve/single.py
MCPoly/status/Hbond.py
MCPoly/status/__init__.py
MCPoly/status/echart.py
MCPoly/status/gui.py
MCPoly/status/molesplit.py
MCPoly/status/ssfigure.py
MCPoly/status/status.py
MCPoly/version/__init__.py
MCPoly/version/version.py
MCPoly/view3d/__init__.py
MCPoly/view3d/view3d.py
MCPoly/vis/__init__.py
MCPoly/vis/vis.py
MCPoly-0.6.1.dist-info/LICENSE
MCPoly-0.6.1.dist-info/METADATA
MCPoly-0.6.1.dist-info/WHEEL
MCPoly-0.6.1.dist-info/top_level.txt
MCPoly-0.6.1.dist-info/RECORD
