Metadata-Version: 2.1
Name: MCPoly
Version: 0.6.1
Summary: Useful tools for Computational Chemistry for polymers
Home-page: https://github.com/Omicron-Fluor/MCPoly/
Author: Omicron Fluor
Author-email: cxs454@student.bham.ac.uk
License: MIT
Keywords: ORCA,Mechanical Property,Computational Chemistry
License-File: LICENSE
Requires-Dist: ase >=3.20.0
Requires-Dist: ipywidgets >=8.0.0
Requires-Dist: numpy >=1.22.0
Requires-Dist: matplotlib >=3.6.0
Requires-Dist: pandas >=1.4.0
Requires-Dist: seaborn >=0.11.0
Requires-Dist: py3dmol >=2.0.0
Requires-Dist: rdkit >=2022.9.3
Requires-Dist: scikit-learn >=1.1.2
